{
  "parent": "custom_advancements:challenges/one_hard_ore",
  "display": {
    "icon": {
      "item": "minecraft:diamond_ore"
    },
    "title": "Geologist",
    "description": "Acquire all ore blocks",
    "frame": "task",
    "show_toast": true,
    "announce_to_chat": true,
    "hidden": false
  },
  "criteria": {
    "gold": {
      "trigger": "minecraft:inventory_changed",
      "conditions": {
        "items": [
          {
            "item": "minecraft:gold_ore"
          }
        ]
      }
    },
	"iron": {
      "trigger": "minecraft:inventory_changed",
      "conditions": {
        "items": [
          {
            "item": "minecraft:iron_ore"
          }
        ]
      }
    },
	"coal": {
      "trigger": "minecraft:inventory_changed",
      "conditions": {
        "items": [
          {
            "item": "minecraft:coal_ore"
          }
        ]
      }
    },
	"lapis": {
      "trigger": "minecraft:inventory_changed",
      "conditions": {
        "items": [
          {
            "item": "minecraft:lapis_ore"
          }
        ]
      }
    },
	"diamond": {
      "trigger": "minecraft:inventory_changed",
      "conditions": {
        "items": [
          {
            "item": "minecraft:diamond_ore"
          }
        ]
      }
    },
	"redstone": {
      "trigger": "minecraft:inventory_changed",
      "conditions": {
        "items": [
          {
            "item": "minecraft:redstone_ore"
          }
        ]
      }
    },
	"emerald": {
      "trigger": "minecraft:inventory_changed",
      "conditions": {
        "items": [
          {
            "item": "minecraft:emerald_ore"
          }
        ]
      }
    },
	"quartz": {
      "trigger": "minecraft:inventory_changed",
      "conditions": {
        "items": [
          {
            "item": "minecraft:nether_quartz_ore"
          }
        ]
      }
    }
  }
}